rest_registration/__init__.py
rest_registration/_version.py
rest_registration/admin.py
rest_registration/apps.py
rest_registration/auth_token_managers.py
rest_registration/checks.py
rest_registration/enums.py
rest_registration/exceptions.py
rest_registration/models.py
rest_registration/settings.py
rest_registration/settings_fields.py
rest_registration/signals.py
rest_registration/tests.py
rest_registration/verification_notifications.py
rest_registration/views.py
rest_registration/api/__init__.py
rest_registration/api/serializers.py
rest_registration/api/urls.py
rest_registration/api/views/__init__.py
rest_registration/api/views/base.py
rest_registration/api/views/change_password.py
rest_registration/api/views/login.py
rest_registration/api/views/profile.py
rest_registration/api/views/register.py
rest_registration/api/views/register_email.py
rest_registration/api/views/reset_password.py
rest_registration/contrib/__init__.py
rest_registration/contrib/verification_redirects/__init__.py
rest_registration/contrib/verification_redirects/admin.py
rest_registration/contrib/verification_redirects/apps.py
rest_registration/contrib/verification_redirects/models.py
rest_registration/contrib/verification_redirects/settings.py
rest_registration/contrib/verification_redirects/urls.py
rest_registration/contrib/verification_redirects/views.py
rest_registration/contrib/verification_redirects/migrations/__init__.py
rest_registration/locale/de/LC_MESSAGES/django.po
rest_registration/locale/fr/LC_MESSAGES/django.po
rest_registration/locale/id/LC_MESSAGES/django.po
rest_registration/locale/pt_BR/LC_MESSAGES/django.po
rest_registration/migrations/__init__.py
rest_registration/notifications/__init__.py
rest_registration/notifications/email.py
rest_registration/notifications/enums.py
rest_registration/signers/__init__.py
rest_registration/signers/register.py
rest_registration/signers/register_email.py
rest_registration/signers/reset_password.py
django_rest_registration-0.9.0.dist-info/LICENSE
django_rest_registration-0.9.0.dist-info/METADATA
django_rest_registration-0.9.0.dist-info/WHEEL
django_rest_registration-0.9.0.dist-info/top_level.txt
django_rest_registration-0.9.0.dist-info/RECORD
