Metadata-Version: 2.1
Name: django-rest-registration
Version: 0.9.0
Summary: User registration REST API, based on django-rest-framework
Author-email: Andrzej Pragacz <apragacz@o2.pl>
License: The MIT License (MIT)
Project-URL: homepage, https://github.com/apragacz/django-rest-registration
Project-URL: Bug Tracker, https://github.com/apragacz/django-rest-registration/issues
Project-URL: Documentation, https://django-rest-registration.readthedocs.io/
Project-URL: Source Code, https://github.com/apragacz/django-rest-registration
Keywords: django,rest,api,auth,rest-framework,registration,register,login,reset-password,register-email,change-email,sign-up,sign-in
Classifier: Development Status :: 4 - Beta
Classifier: Environment :: Web Environment
Classifier: Framework :: Django
Classifier: Framework :: Django :: 2.0
Classifier: Framework :: Django :: 3.0
Classifier: Framework :: Django :: 4.0
Classifier: Intended Audience :: Developers
Classifier: License :: OSI Approved :: MIT License
Classifier: Operating System :: OS Independent
Classifier: Programming Language :: Python
Classifier: Programming Language :: Python :: 3
Classifier: Programming Language :: Python :: 3 :: Only
Classifier: Topic :: Internet
Classifier: Topic :: Internet :: WWW/HTTP
Requires-Python: >=3.7
License-File: LICENSE
Requires-Dist: Django>=2.0
Requires-Dist: djangorestframework>=3.3
